{
  "development": {
    "hub_api_url": "None",
    "proxy_initial_sats": 20000,
    "proxy_new_nodes": 4,
    "proxy_lnd_ip": "proxy.sphinx",
    "proxy_admin_token": "r46bnf8ibrhbb424heba",
    "proxy_admin_url": "http://proxy.sphinx:5050",
    "dont_ping_hub": true,
    "proxy_lnd_port": "11111",
    "proxy_tls_location": "/proxy/cert/tls.cert",
    "proxy_macaroons_dir": "/proxy/macaroons",
    "node_ip": "127.0.0.1",
    "lnd_ip": "dave-lnd.sphinx",
    "lnd_port": "10012",
    "tls_location": "/relay/dave/.lnd/tls.cert",
    "macaroon_location": "/relay/dave/.lnd/data/chain/bitcoin/regtest/admin.macaroon",
    "node_http_protocol": "http",
    "node_http_port": "3004",
    "tribes_mqtt_port": "1883",
    "tribes_insecure": true,
    "public_url": "127.0.0.1:3004",
    "connect_ui": true,
    "logging_level": "debug",
    "proxy_hd_keys": true,
    "allow_swarm_invite": true,
    "host_name": "http://dave.sphinx:3004",
    "media_host": "meme.sphinx:5555"
  },
  "gitactionenv": {
    "hub_api_url": "None",
    "proxy_initial_sats": 20000,
    "proxy_new_nodes": 4,
    "proxy_lnd_ip": "proxy.sphinx",
    "proxy_admin_token": "r46bnf8ibrhbb424heba",
    "proxy_admin_url": "http://proxy.sphinx:5050",
    "dont_ping_hub": true,
    "proxy_lnd_port": "11111",
    "proxy_tls_location": "/proxy/cert/tls.cert",
    "proxy_macaroons_dir": "/proxy/macaroons",
    "node_ip": "127.0.0.1",
    "lnd_ip": "dave-lnd.sphinx",
    "lnd_port": "10012",
    "tls_location": "/relay/dave/.lnd/tls.cert",
    "macaroon_location": "/relay/dave/.lnd/data/chain/bitcoin/regtest/admin.macaroon",
    "node_http_protocol": "http",
    "node_http_port": "3004",
    "tribes_mqtt_port": "1883",
    "tribes_insecure": true,
    "public_url": "127.0.0.1:3004",
    "connect_ui": true,
    "logging_level": "debug",
    "proxy_hd_keys": true,
    "allow_swarm_invite": true,
    "host_name": "http://dave.sphinx:3004",
    "media_host": "meme.sphinx:5555"
  }
}
